CallFlow-1.1.2.data/data/data/caliper-cali/caliper-ex.cali
CallFlow-1.1.2.data/data/data/caliper-cali/caliper-ex.json
CallFlow-1.1.2.data/data/data/caliper-cali/callflow.config.json
CallFlow-1.1.2.data/data/data/caliper-lulesh-json/callflow.config.json
CallFlow-1.1.2.data/data/data/caliper-lulesh-json/lulesh-sample-annotation-profile.json
CallFlow-1.1.2.data/data/examples/%callflow-ipython-magic.ipynb
CallFlow-1.1.2.data/data/examples/CallFlow-python-interface-demo.ipynb
callflow/__init__.py
callflow/callflow.py
callflow/logger.py
callflow/timer.py
callflow/utils.py
callflow/version.py
callflow/algorithms/__init__.py
callflow/algorithms/bland_altman.py
callflow/algorithms/deltacon_similarity.py
callflow/algorithms/k_medoids.py
callflow/algorithms/prog_kmeans.py
callflow/algorithms/wl_distance.py
callflow/datastructures/__init__.py
callflow/datastructures/ensemblegraph.py
callflow/datastructures/graphframe.py
callflow/datastructures/supergraph.py
callflow/layout/__init__.py
callflow/layout/hierarchy.py
callflow/layout/node_link.py
callflow/layout/sankey.py
callflow/modules/__init__.py
callflow/modules/auxiliary.py
callflow/modules/auxiliary_fast.py
callflow/modules/auxiliary_single.py
callflow/modules/boxplot.py
callflow/modules/diff_view.py
callflow/modules/function_list.py
callflow/modules/gradients.py
callflow/modules/histogram_generic.py
callflow/modules/histogram_mini.py
callflow/modules/histogram_rank.py
callflow/modules/parameter_projection.py
callflow/modules/runtime_scatterplot.py
callflow/modules/split_callee.py
callflow/modules/split_entry.py
callflow/modules/tooltip.py
callflow/operations/__init__.py
callflow/operations/argparser.py
callflow/operations/filter.py
callflow/operations/group.py
callflow/operations/process.py
callflow/server/__init__.py
callflow/server/api_provider.py
callflow/server/callflow_server.py
callflow/server/manager.py
callflow/server/notebook_server.py
callflow/server/socket_provider.py
CallFlow-1.1.2.dist-info/LICENSE
CallFlow-1.1.2.dist-info/METADATA
CallFlow-1.1.2.dist-info/NOTICE
CallFlow-1.1.2.dist-info/WHEEL
CallFlow-1.1.2.dist-info/entry_points.txt
CallFlow-1.1.2.dist-info/top_level.txt
CallFlow-1.1.2.dist-info/RECORD
