Metadata-Version: 2.1
Name: CallFlow
Version: 1.1.2
Summary: UNKNOWN
Home-page: https://github.com/LLNL/CallFlow
Author: Suraj Kesavan
Author-email: spkesavan@ucdavis.edu
License: MIT
Platform: UNKNOWN
Classifier: Development Status :: 3 - Alpha
Classifier: License :: OSI Approved :: MIT License
Requires-Dist: flask-socketio
Requires-Dist: ipython
Requires-Dist: colorlog
Requires-Dist: jsonschema
Requires-Dist: numpy
Requires-Dist: scipy
Requires-Dist: pandas
Requires-Dist: scikit-learn
Requires-Dist: statsmodels
Requires-Dist: hatchet
Requires-Dist: networkx
Requires-Dist: matplotlib
